swh/__init__.py
swh/archiver/__init__.py
swh/archiver/checker.py
swh/archiver/copier.py
swh/archiver/db.py
swh/archiver/director.py
swh/archiver/storage.py
swh/archiver/tasks.py
swh/archiver/updater.py
swh/archiver/worker.py
swh/archiver/sql/10-swh-init.sql
swh/archiver/sql/30-swh-schema.sql
swh/archiver/sql/40-swh-func.sql
swh/archiver/sql/50-swh-data.sql
swh/archiver/tests/__init__.py
swh/archiver/tests/conftest.py
swh/archiver/tests/test_archiver.py
swh/archiver/tests/test_archiver_storage.py
swh/archiver/tests/test_checker.py
swh.archiver-0.0.6.dist-info/METADATA
swh.archiver-0.0.6.dist-info/WHEEL
swh.archiver-0.0.6.dist-info/top_level.txt
swh.archiver-0.0.6.dist-info/RECORD
