Metadata-Version: 2.1
Name: swh.archiver
Version: 0.0.6
Summary: Software Heritage archiver
Home-page: https://forge.softwareheritage.org/diffusion/DARC/
Author: Software Heritage developers
Author-email: swh-devel@inria.fr
License: UNKNOWN
Project-URL: Bug Reports, https://forge.softwareheritage.org/maniphest
Project-URL: Funding, https://www.softwareheritage.org/donate
Project-URL: Source, https://forge.softwareheritage.org/source/swh-archiver
Platform: UNKNOWN
Classifier: Programming Language :: Python :: 3
Classifier: Intended Audience :: Developers
Classifier: License :: OSI Approved :: GNU General Public License v3 (GPLv3)
Classifier: Operating System :: OS Independent
Classifier: Development Status :: 5 - Production/Stable
Requires-Dist: click
Requires-Dist: kafka-python
Requires-Dist: psycopg2
Requires-Dist: vcversioner
Requires-Dist: swh.core (>=0.0.54)
Requires-Dist: swh.journal (>=0.0.5)
Requires-Dist: swh.model (>=0.0.27)
Requires-Dist: swh.objstorage (>=0.0.17)
Requires-Dist: swh.scheduler (>=0.0.39)
Provides-Extra: testing
Requires-Dist: pytest (<4) ; extra == 'testing'
Requires-Dist: pytest-postgresql ; extra == 'testing'
